annotate/__init__.py
annotate/api.py
annotate/attributes.py
annotate/decorators.py
annotate/decorators.pyi
annotate/models.py
annotate/py.typed
annotate/utils.py
tombulled_annotate-0.1.15.dist-info/LICENSE
tombulled_annotate-0.1.15.dist-info/WHEEL
tombulled_annotate-0.1.15.dist-info/METADATA
tombulled_annotate-0.1.15.dist-info/RECORD
