Metadata-Version: 2.1
Name: tombulled-annotate
Version: 0.1.15
Summary: Python Annotation System
Home-page: https://github.com/tombulled/annotate
License: MIT
Keywords: python,annotate,annotation,marker,label,mark,tag
Author: Tom Bulled
Author-email: 26026015+tombulled@users.noreply.github.com
Requires-Python: >=3.8,<4.0
Classifier: License :: OSI Approved :: MIT License
Classifier: Programming Language :: Python :: 3
Classifier: Programming Language :: Python :: 3.8
Classifier: Programming Language :: Python :: 3.9
Classifier: Programming Language :: Python :: 3.10
Classifier: Programming Language :: Python :: 3.11
Requires-Dist: attribute (>=0.1.4,<0.2.0)
Requires-Dist: typing-extensions (>=4.3.0,<5.0.0)
Project-URL: Repository, https://github.com/tombulled/annotate
